auto_group/__init__.py
auto_group/advanced.py
auto_group/tools.py
auto_group-1.3.1.dist-info/LICENSE
auto_group-1.3.1.dist-info/METADATA
auto_group-1.3.1.dist-info/WHEEL
auto_group-1.3.1.dist-info/top_level.txt
auto_group-1.3.1.dist-info/RECORD
