Metadata-Version: 2.1
Name: auto-group
Version: 1.3.1
Summary: Tools for creating tree structures from flat list of dicts
Home-page: https://gitlab.com/alda78/auto-group
Author: Ales Adamek, Filip Cima
Author-email: alda78@seznam.cz
Classifier: Programming Language :: Python :: 3
Classifier: License :: OSI Approved :: MIT License
Classifier: Operating System :: OS Independent
Requires-Python: >=3.6
License-File: LICENSE
